tmt/__init__.py
tmt/cli.py
tmt_timezone-1.0.0.dist-info/licenses/LICENSE
tmt_timezone-1.0.0.dist-info/METADATA
tmt_timezone-1.0.0.dist-info/WHEEL
tmt_timezone-1.0.0.dist-info/entry_points.txt
tmt_timezone-1.0.0.dist-info/top_level.txt
tmt_timezone-1.0.0.dist-info/RECORD
