Metadata-Version: 2.4
Name: tmt-timezone
Version: 1.0.0
Summary: A CLI tool to get current time in different timezones
Home-page: https://github.com/tmt/tmt
Author: TMT Developer
Author-email: TMT Developer <dev@tmt.com>
License: MIT
Classifier: Development Status :: 4 - Beta
Classifier: Intended Audience :: Developers
Classifier: License :: OSI Approved :: MIT License
Classifier: Operating System :: OS Independent
Classifier: Programming Language :: Python :: 3
Classifier: Programming Language :: Python :: 3.7
Classifier: Programming Language :: Python :: 3.8
Classifier: Programming Language :: Python :: 3.9
Classifier: Programming Language :: Python :: 3.10
Classifier: Programming Language :: Python :: 3.11
Requires-Python: >=3.7
License-File: LICENSE
Requires-Dist: pytz>=2021.1
Dynamic: author
Dynamic: home-page
Dynamic: license-file
Dynamic: requires-python
